pypox/__init__.py
pypox/_types.py
pypox/application.py
pypox/authentication.py
pypox/openapi/__init__.py
pypox/openapi/main.py
pypox/processing/__init__.py
pypox/processing/base.py
pypox/processing/validators/__init__.py
pypox/processing/validators/base.py
pypox/processing/validators/cookies.py
pypox/processing/validators/form.py
pypox/processing/validators/header.py
pypox/processing/validators/htmx.py
pypox/processing/validators/json.py
pypox/processing/validators/path.py
pypox/processing/validators/query.py
pypox/router.py
pypox/status.py
pypox-2.2.2.dist-info/LICENCE.md
pypox-2.2.2.dist-info/METADATA
pypox-2.2.2.dist-info/WHEEL
pypox-2.2.2.dist-info/RECORD
