Metadata-Version: 2.1
Name: pypox
Version: 2.2.2
Summary: 
Author: karl robeck alferez
Author-email: karlalferezfx@gmail.com
Requires-Python: >=3.12,<4.0
Classifier: Programming Language :: Python :: 3
Classifier: Programming Language :: Python :: 3.12
Requires-Dist: httpx (>=0.26.0)
Requires-Dist: orjson (>=3.9.12)
Requires-Dist: pydantic (>=2.6.0)
Requires-Dist: python-jose[cryptography] (>=3.3.0,<4.0.0)
Requires-Dist: starlette (>=0.35.1)
Requires-Dist: uvicorn[standard] (>=0.25.0)
